networking_fujitsu/__init__.py
networking_fujitsu/_i18n.py
networking_fujitsu/version.py
networking_fujitsu/ml2/__init__.py
networking_fujitsu/ml2/cfab/__init__.py
networking_fujitsu/ml2/cfab/cfabdriver.py
networking_fujitsu/ml2/cfab/mech_cfab.py
networking_fujitsu/ml2/common/__init__.py
networking_fujitsu/ml2/common/tunnel_caller.py
networking_fujitsu/ml2/common/type_vxlan.py
networking_fujitsu/ml2/common/utils.py
networking_fujitsu/ml2/common/ovsdb/__init__.py
networking_fujitsu/ml2/common/ovsdb/base_connection.py
networking_fujitsu/ml2/common/ovsdb/constants.py
networking_fujitsu/ml2/common/ovsdb/ovsdb_writer.py
networking_fujitsu/ml2/fossw/__init__.py
networking_fujitsu/ml2/fossw/client.py
networking_fujitsu/ml2/fossw/fossw_vlandriver.py
networking_fujitsu/ml2/fossw/fossw_vxlandriver.py
networking_fujitsu/ml2/fossw/mech_fossw.py
networking_fujitsu/tests/__init__.py
networking_fujitsu/tests/unit/__init__.py
networking_fujitsu/tests/unit/ml2/__init__.py
networking_fujitsu/tests/unit/ml2/cfab/__init__.py
networking_fujitsu/tests/unit/ml2/cfab/test_cfabdriver.py
networking_fujitsu/tests/unit/ml2/cfab/test_mech_cfab.py
networking_fujitsu/tests/unit/ml2/common/__init__.py
networking_fujitsu/tests/unit/ml2/common/helper.py
networking_fujitsu/tests/unit/ml2/common/test_tunnel_caller.py
networking_fujitsu/tests/unit/ml2/common/test_type_vxlan.py
networking_fujitsu/tests/unit/ml2/common/test_utils.py
networking_fujitsu/tests/unit/ml2/common/ovsdb/__init__.py
networking_fujitsu/tests/unit/ml2/common/ovsdb/test_base_connection.py
networking_fujitsu/tests/unit/ml2/common/ovsdb/test_ovsdb_writer.py
networking_fujitsu/tests/unit/ml2/fossw/__init__.py
networking_fujitsu/tests/unit/ml2/fossw/test_client.py
networking_fujitsu/tests/unit/ml2/fossw/test_fossw_vlandriver.py
networking_fujitsu/tests/unit/ml2/fossw/test_fossw_vxlandriver.py
networking_fujitsu/tests/unit/ml2/fossw/test_mech_fossw.py
networking_fujitsu-8.0.0.data/data/etc/neutron/plugins/ml2/ml2_conf_fujitsu_cfab.ini
networking_fujitsu-8.0.0.dist-info/AUTHORS
networking_fujitsu-8.0.0.dist-info/LICENSE
networking_fujitsu-8.0.0.dist-info/METADATA
networking_fujitsu-8.0.0.dist-info/WHEEL
networking_fujitsu-8.0.0.dist-info/entry_points.txt
networking_fujitsu-8.0.0.dist-info/pbr.json
networking_fujitsu-8.0.0.dist-info/top_level.txt
networking_fujitsu-8.0.0.dist-info/RECORD
