Metadata-Version: 2.1
Name: networking-fujitsu
Version: 8.0.0
Summary: FUJITSU ML2 plugins/drivers for OpenStack Neutron
Home-page: https://github.com/openstack/networking-fujitsu
Author: OpenStack
Author-email: openstack-dev@lists.openstack.org
License: UNKNOWN
Platform: UNKNOWN
Classifier: Environment :: OpenStack
Classifier: Intended Audience :: Information Technology
Classifier: Intended Audience :: System Administrators
Classifier: License :: OSI Approved :: Apache Software License
Classifier: Operating System :: POSIX :: Linux
Classifier: Programming Language :: Python
Classifier: Programming Language :: Python :: 2
Classifier: Programming Language :: Python :: 2.7
Classifier: Programming Language :: Python :: 3
Classifier: Programming Language :: Python :: 3.5
Requires-Dist: neutron-lib (>=1.18.0)
Requires-Dist: oslo.i18n (>=3.15.3)
Requires-Dist: oslo.log (>=3.36.0)
Requires-Dist: oslo.utils (>=3.33.0)
Requires-Dist: paramiko (>=2.0.0)
Requires-Dist: pbr (!=2.1.0,>=2.0.0)
Requires-Dist: neutron (>=13.0.0.0b1)
